easyenv/__init__.py
easyenv/cache.py
easyenv/cli.py
easyenv/config.py
easyenv/dsl.py
easyenv/lock.py
easyenv/runner.py
easyenv/sbom.py
easyenv/spec.py
easyenv/tui.py
easyenv/uv_integration.py
easyenv/welcome.py
easyenv_cli-0.1.6.dist-info/METADATA
easyenv_cli-0.1.6.dist-info/WHEEL
easyenv_cli-0.1.6.dist-info/entry_points.txt
easyenv_cli-0.1.6.dist-info/licenses/LICENSE
easyenv_cli-0.1.6.dist-info/RECORD
