Metadata-Version: 2.3
Name: easyenv-cli
Version: 0.1.6
Summary: Ephemeral, reproducible, cached development environment
Project-URL: Homepage, https://github.com/ruslanlap/EasyEnv
Project-URL: Documentation, https://github.com/ruslanlap/EasyEnv/blob/master/README.md
Project-URL: Repository, https://github.com/ruslanlap/EasyEnv
Project-URL: Issues, https://github.com/ruslanlap/EasyEnv/issues
Author: EasyEnv by @ruslanlap
License: MIT License
License-File: LICENSE
Keywords: cache,development,environment,ephemeral,reproducible
Classifier: Development Status :: 4 - Beta
Classifier: Intended Audience :: Developers
Classifier: License :: OSI Approved :: MIT License
Classifier: Programming Language :: Python :: 3
Classifier: Programming Language :: Python :: 3.11
Classifier: Programming Language :: Python :: 3.12
Classifier: Topic :: Software Development :: Build Tools
Requires-Python: >=3.11
Requires-Dist: platformdirs>=4.0.0
Requires-Dist: pydantic>=2.0.0
Requires-Dist: pyyaml>=6.0
Requires-Dist: rich>=13.0.0
Requires-Dist: textual>=0.47.0
Requires-Dist: typer>=0.12.0
Provides-Extra: dev
Requires-Dist: mypy>=1.0.0; extra == 'dev'
Requires-Dist: pytest-cov>=4.0.0; extra == 'dev'
Requires-Dist: pytest-mock>=3.12.0; extra == 'dev'
Requires-Dist: pytest>=7.0.0; extra == 'dev'
Requires-Dist: ruff>=0.1.0; extra == 'dev'
Requires-Dist: types-pyyaml; extra == 'dev'
